AUTHORS.md
CHANGELOG.md
CONTRIBUTING.md
LICENSE
MANIFEST.in
README.md
setup.cfg
setup.py
commit_checker/__init__.py
commit_checker/cli.py
commit_checker/commit_checker.py
commit_checker.egg-info/PKG-INFO
commit_checker.egg-info/SOURCES.txt
commit_checker.egg-info/dependency_links.txt
commit_checker.egg-info/entry_points.txt
commit_checker.egg-info/not-zip-safe
commit_checker.egg-info/top_level.txt
docs/Makefile
docs/conf.py
docs/make.bat
tests/__init__.py
tests/test_commit_checker.py