Metadata-Version: 2.1
Name: commit-checker
Version: 0.0.1.dev0
Summary: This is a quality tool with the goal to automate some of the reviewing work of pull requests in Bitbucket (or any other environment)
Home-page: https://github.com/spiked-maniac/commit_checker
Author: Niels van der Schans
Author-email: nvdschans@gmail.com
License: Apache Software License 2.0
Keywords: commit_checker
Platform: UNKNOWN
Classifier: Development Status :: 2 - Pre-Alpha
Classifier: Intended Audience :: Developers
Classifier: License :: OSI Approved :: Apache Software License
Classifier: Natural Language :: English
Classifier: Programming Language :: Python :: 3
Classifier: Programming Language :: Python :: 3.5
Classifier: Programming Language :: Python :: 3.6
Classifier: Programming Language :: Python :: 3.7
